drfs/__init__.py
drfs/_version.py
drfs/agnostic.py
drfs/config_default.yaml
drfs/luigi.py
drfs/path.py
drfs/settings.py
drfs/structure.py
drfs/util.py
drfs/filesystems/__init__.py
drfs/filesystems/azure_blob.py
drfs/filesystems/azure_datalake.py
drfs/filesystems/base.py
drfs/filesystems/gcs.py
drfs/filesystems/local.py
drfs/filesystems/memory.py
drfs/filesystems/s3.py
drfs/filesystems/util.py
drfs-0.3.6.2.dist-info/LICENSE
drfs-0.3.6.2.dist-info/METADATA
drfs-0.3.6.2.dist-info/WHEEL
drfs-0.3.6.2.dist-info/top_level.txt
drfs-0.3.6.2.dist-info/RECORD
