Metadata-Version: 2.1
Name: drfs
Version: 0.3.6.2
Summary: Storage-type-agnostic file access + file structure for your project
Home-page: https://github.com/datarevenue-berlin/drfs
Author: Data Revenue GmbH
Author-email: alan@datarevenue.com
License: MIT license
Keywords: drfs
Platform: UNKNOWN
Classifier: Development Status :: 2 - Pre-Alpha
Classifier: Intended Audience :: Developers
Classifier: License :: OSI Approved :: MIT License
Classifier: Natural Language :: English
Classifier: Programming Language :: Python :: 3.6
Classifier: Programming Language :: Python :: 3.7
License-File: LICENSE
Requires-Dist: pytz
Requires-Dist: urlpath (==1.1.*)
Requires-Dist: fsspec (>=0.8.0)
Requires-Dist: confuse (>=1.0.0)
